pytwisty.py
pytwisty-0.0.1.dist-info/LICENSE.txt
pytwisty-0.0.1.dist-info/METADATA
pytwisty-0.0.1.dist-info/WHEEL
pytwisty-0.0.1.dist-info/top_level.txt
pytwisty-0.0.1.dist-info/RECORD
