Metadata-Version: 2.1
Name: pytwisty
Version: 0.0.1
Summary: Solve 1x2x2, 1x2x3, and 2x2x2 Rubik's cube puzzles
Home-page: UNKNOWN
Author: Prakhar Gupta
Author-email: pkrdps@gmail.com
License: UNKNOWN
Platform: UNKNOWN
Classifier: License :: OSI Approved :: MIT License
Classifier: Operating System :: OS Independent
Classifier: Programming Language :: Python :: 3
Classifier: Topic :: Games/Entertainment :: Puzzle Games
Classifier: Topic :: Scientific/Engineering :: Artificial Intelligence
